NetHyTech_HindiTTS/__init__.py
NetHyTech_HindiTTS-1.1.dist-info/METADATA
NetHyTech_HindiTTS-1.1.dist-info/WHEEL
NetHyTech_HindiTTS-1.1.dist-info/entry_points.txt
NetHyTech_HindiTTS-1.1.dist-info/top_level.txt
NetHyTech_HindiTTS-1.1.dist-info/RECORD
