Metadata-Version: 2.1
Name: NetHyTech-HindiTTS
Version: 1.1
Summary: Text To Speech In British Brian Voice
Home-page: https://github.com/AnubhavChaturvedi-GitHub/NetHyTech-TTS.git
Author: Anubhav Chaturvedi
Author-email: chaturvedianubhav520@example.com
Project-URL: Source Code, https://github.com/AnubhavChaturvedi-GitHub/NetHyTech-TTS.git
Project-URL: Demo Video, https://www.youtube.com/channel/UC7YDMgu0dMRZotLMuB3oEcQ
Classifier: Development Status :: 5 - Production/Stable
Classifier: Intended Audience :: Developers
Classifier: Topic :: Multimedia :: Sound/Audio :: Speech
Classifier: License :: OSI Approved :: MIT License
Classifier: Programming Language :: Python :: 3
Classifier: Programming Language :: Python :: 3.8
Classifier: Programming Language :: Python :: 3.9
Classifier: Operating System :: OS Independent
Requires-Python: >=3.8
Requires-Dist: selenium
Requires-Dist: webdriver-manager
Requires-Dist: chromedriver-autoinstaller
